{# 
#This is a jinja2 template of the package.xml of ROS2 packages
#
# Written in 13/3/2020
# Written by Rafael Brouzos
#}
<?xml version="1.0"?>
<?xml-model href="http://download.ros.org/schema/package_format3.xsd" schematypens="http://www.w3.org/2001/XMLSchema"?>
<package format="3">
  <name>{{pack.packageName}}</name>
  <version>0.0.0</version>
  <description>{{pack.description}}</description>
  <maintainer email="{{pack.email}}">{{pack.maintainer}}</maintainer>
  <license>{{pack.license}}</license>

  <buildtool_depend>ament_python</buildtool_depend>
  
  <exec_depend>rclpy</exec_depend>
  <exec_depend>interfaces</exec_depend>
  <exec_depend>std_msgs</exec_depend>

  <test_depend>ament_copyright</test_depend>
  <test_depend>ament_flake8</test_depend>
  <test_depend>ament_pep257</test_depend>
  <test_depend>python3-pytest</test_depend>

  <export>
    <build_type>ament_python</build_type>
  </export>
</package>
